flake518-1.6.0.dist-info/METADATA
flake518-1.6.0.dist-info/WHEEL
flake518-1.6.0.dist-info/entry_points.txt
flake518-1.6.0.dist-info/licenses/LICENSE
flake518/__init__.py
flake518/__main__.py
flake518/adapter.py
flake518-1.6.0.dist-info/RECORD
