Metadata-Version: 2.1
Name: flake518
Version: 1.6.0
Summary: A small wrapper around flake8 to support PEP518 pyproject.toml as configuration file.
Home-page: https://github.com/carstencodes/flake518
Author-Email: Carsten Igel <cig@bite-that-bit.de>
License: MIT License
Classifier: Development Status :: 5 - Production/Stable
Classifier: Environment :: Console
Classifier: Framework :: Flake8
Classifier: Intended Audience :: Developers
Classifier: License :: OSI Approved :: MIT License
Classifier: Programming Language :: Python
Classifier: Programming Language :: Python :: 3
Classifier: Programming Language :: Python :: 3.9
Classifier: Programming Language :: Python :: 3.10
Classifier: Programming Language :: Python :: 3.11
Classifier: Topic :: Software Development :: Libraries :: Python Modules
Classifier: Topic :: Software Development :: Quality Assurance
Classifier: Typing :: Typed
Project-URL: Homepage, https://github.com/carstencodes/flake518
Requires-Python: <4,>=3.9
Requires-Dist: tomli>=0.10.2; python_version < "3.11"
Requires-Dist: flake8>=3.0.0
